cod4rcon/__init__.py
cod4rcon/rcon_handler.py
Cod4_Rcon_sockets-0.0.2.dist-info/LICENSE
Cod4_Rcon_sockets-0.0.2.dist-info/METADATA
Cod4_Rcon_sockets-0.0.2.dist-info/WHEEL
Cod4_Rcon_sockets-0.0.2.dist-info/top_level.txt
Cod4_Rcon_sockets-0.0.2.dist-info/RECORD
