Metadata-Version: 2.1
Name: Cod4-Rcon-sockets
Version: 0.0.2
Summary: Python Rcon handler for Cod4
Home-page: https://github.com/Ckoelewyn/discon
Author: Corey Koelewyn
Author-email: Corey.koelewyn@gmail.com
License: UNKNOWN
Project-URL: Bug Tracker, https://github.com/Ckoelewyn/discon/issues
Platform: UNKNOWN
Classifier: Programming Language :: Python :: 3
Classifier: License :: OSI Approved :: MIT License
Classifier: Operating System :: POSIX :: Linux
Requires-Python: >=3.6
License-File: LICENSE
